ovos_PHAL_plugin_pulseaudio/__init__.py
ovos_PHAL_plugin_pulseaudio/blop-mark-diangelo.wav
ovos_PHAL_plugin_pulseaudio/version.py
ovos_PHAL_plugin_pulseaudio-0.0.2.dist-info/LICENSE
ovos_PHAL_plugin_pulseaudio-0.0.2.dist-info/METADATA
ovos_PHAL_plugin_pulseaudio-0.0.2.dist-info/WHEEL
ovos_PHAL_plugin_pulseaudio-0.0.2.dist-info/entry_points.txt
ovos_PHAL_plugin_pulseaudio-0.0.2.dist-info/top_level.txt
ovos_PHAL_plugin_pulseaudio-0.0.2.dist-info/zip-safe
ovos_PHAL_plugin_pulseaudio-0.0.2.dist-info/RECORD
